{
  "strategy": "smart",
  "period": "2023ë…„",
  "large_tickers": [
    "ROIV",
    "TME",
    "DB",
    "UHS",
    "HAL"
  ],
  "mega_tickers": [
    "CAT",
    "GE",
    "ORCL",
    "MRK",
    "ASML"
  ],
  "simulation": {
    "tickers": [
      "ROIV",
      "TME",
      "DB",
      "UHS",
      "HAL",
      "CAT",
      "GE",
      "ORCL",
      "MRK",
      "ASML"
    ],
    "start_date": "2023-01-03",
    "end_date": "2023-12-29",
    "initial_capital": 10000,
    "final_value": 13368.099884804247,
    "total_return": 33.68099884804247,
    "annualized_return": 34.2210554869258,
    "mdd": -7.582324620870596,
    "sharpe_ratio": 1.6442546892730614,
    "win_rate": 27.309236947791167,
    "trading_days": 249,
    "best_day": {
      "date": "2023-03-09",
      "return": 5.265572206976739,
      "value": 11718.365161661835,
      "active_positions": 1,
      "cash": 0
    },
    "worst_day": {
      "date": "2023-03-22",
      "return": -2.809723704932873,
      "value": 11466.233679807317,
      "active_positions": 1,
      "cash": 0
    },
    "portfolio_history": [
      {
        "date": "2023-01-03",
        "value": 10000
      },
      {
        "date": "2023-01-04",
        "value": 10357.95138018203
      },
      {
        "date": "2023-01-05",
        "value": 10435.313633414798
      },
      {
        "date": "2023-01-06",
        "value": 10758.020343797036
      },
      {
        "date": "2023-01-09",
        "value": 10727.27313549395
      },
      {
        "date": "2023-01-10",
        "value": 10889.10684372427
      },
      {
        "date": "2023-01-11",
        "value": 10886.48172123706
      },
      {
        "date": "2023-01-12",
        "value": 11062.194553203406
      },
      {
        "date": "2023-01-13",
        "value": 11177.929976858728
      },
      {
        "date": "2023-01-17",
        "value": 11014.047520780285
      },
      {
        "date": "2023-01-18",
        "value": 10817.285151444188
      },
      {
        "date": "2023-01-19",
        "value": 10620.308744052645
      },
      {
        "date": "2023-01-20",
        "value": 10750.502717493726
      },
      {
        "date": "2023-01-23",
        "value": 10767.019009782089
      },
      {
        "date": "2023-01-24",
        "value": 10803.685497090686
      },
      {
        "date": "2023-01-25",
        "value": 10821.26486720158
      },
      {
        "date": "2023-01-26",
        "value": 10885.34436945395
      },
      {
        "date": "2023-01-27",
        "value": 10960.095126311657
      },
      {
        "date": "2023-01-30",
        "value": 10804.517360686543
      },
      {
        "date": "2023-01-31",
        "value": 10749.094314210259
      },
      {
        "date": "2023-02-01",
        "value": 10854.388433673144
      },
      {
        "date": "2023-02-02",
        "value": 10656.821277883588
      },
      {
        "date": "2023-02-03",
        "value": 10564.54840341219
      },
      {
        "date": "2023-02-06",
        "value": 10539.513693968584
      },
      {
        "date": "2023-02-07",
        "value": 10477.859813532365
      },
      {
        "date": "2023-02-08",
        "value": 10406.983618662203
      },
      {
        "date": "2023-02-09",
        "value": 10330.383040119694
      },
      {
        "date": "2023-02-10",
        "value": 10394.316592690828
      },
      {
        "date": "2023-02-13",
        "value": 10572.05284824514
      },
      {
        "date": "2023-02-14",
        "value": 10682.019128954851
      },
      {
        "date": "2023-02-15",
        "value": 10839.294465717356
      },
      {
        "date": "2023-02-16",
        "value": 10747.22776968506
      },
      {
        "date": "2023-02-17",
        "value": 10618.08371675101
      },
      {
        "date": "2023-02-21",
        "value": 10518.3478954372
      },
      {
        "date": "2023-02-22",
        "value": 10637.263968485622
      },
      {
        "date": "2023-02-23",
        "value": 10605.29812201641
      },
      {
        "date": "2023-02-24",
        "value": 10683.294836991498
      },
      {
        "date": "2023-02-27",
        "value": 10720.3771529138
      },
      {
        "date": "2023-02-28",
        "value": 10831.62286092557
      },
      {
        "date": "2023-03-01",
        "value": 10758.73889613816
      },
      {
        "date": "2023-03-02",
        "value": 10960.769393369894
      },
      {
        "date": "2023-03-03",
        "value": 11045.158285834714
      },
      {
        "date": "2023-03-06",
        "value": 11142.429473934873
      },
      {
        "date": "2023-03-07",
        "value": 11056.679330328912
      },
      {
        "date": "2023-03-08",
        "value": 11132.191576008145
      },
      {
        "date": "2023-03-09",
        "value": 11718.365161661835
      },
      {
        "date": "2023-03-10",
        "value": 11646.689958133635
      },
      {
        "date": "2023-03-13",
        "value": 11386.880672711639
      },
      {
        "date": "2023-03-14",
        "value": 11668.4501403097
      },
      {
        "date": "2023-03-15",
        "value": 11487.991382473107
      },
      {
        "date": "2023-03-16",
        "value": 11770.840277373223
      },
      {
        "date": "2023-03-17",
        "value": 11555.823345074585
      },
      {
        "date": "2023-03-20",
        "value": 11508.464698816286
      },
      {
        "date": "2023-03-21",
        "value": 11797.716929002376
      },
      {
        "date": "2023-03-22",
        "value": 11466.233679807317
      },
      {
        "date": "2023-03-23",
        "value": 11722.204683323143
      },
      {
        "date": "2023-03-24",
        "value": 11694.047364636795
      },
      {
        "date": "2023-03-27",
        "value": 11942.341804340282
      },
      {
        "date": "2023-03-28",
        "value": 11920.581622164216
      },
      {
        "date": "2023-03-29",
        "value": 12038.329845872971
      },
      {
        "date": "2023-03-30",
        "value": 12037.04793906064
      },
      {
        "date": "2023-03-31",
        "value": 12235.428597167127
      },
      {
        "date": "2023-04-03",
        "value": 12404.368790019798
      },
      {
        "date": "2023-04-04",
        "value": 12165.036540206396
      },
      {
        "date": "2023-04-05",
        "value": 12062.645163387735
      },
      {
        "date": "2023-04-06",
        "value": 11979.456353896163
      },
      {
        "date": "2023-04-10",
        "value": 12076.725062486046
      },
      {
        "date": "2023-04-11",
        "value": 12019.132237566433
      },
      {
        "date": "2023-04-12",
        "value": 12043.447555081199
      },
      {
        "date": "2023-04-13",
        "value": 12069.046019163432
      },
      {
        "date": "2023-04-14",
        "value": 12214.94784229312
      },
      {
        "date": "2023-04-17",
        "value": 12385.168702202986
      },
      {
        "date": "2023-04-18",
        "value": 12602.744489105737
      },
      {
        "date": "2023-04-19",
        "value": 12674.415973368523
      },
      {
        "date": "2023-04-20",
        "value": 12767.846400052236
      },
      {
        "date": "2023-04-21",
        "value": 12735.849559704582
      },
      {
        "date": "2023-04-24",
        "value": 12817.760181649235
      },
      {
        "date": "2023-04-25",
        "value": 12598.904967444429
      },
      {
        "date": "2023-04-26",
        "value": 12313.497217940198
      },
      {
        "date": "2023-04-27",
        "value": 12550.270613149485
      },
      {
        "date": "2023-04-28",
        "value": 12666.738169801043
      },
      {
        "date": "2023-05-01",
        "value": 12949.584585190885
      },
      {
        "date": "2023-05-02",
        "value": 12991.821802975544
      },
      {
        "date": "2023-05-03",
        "value": 13025.098070625258
      },
      {
        "date": "2023-05-04",
        "value": 12711.53300243468
      },
      {
        "date": "2023-05-05",
        "value": 12829.279986388297
      },
      {
        "date": "2023-05-08",
        "value": 12916.309557296316
      },
      {
        "date": "2023-05-09",
        "value": 12926.547455223044
      },
      {
        "date": "2023-05-10",
        "value": 12739.689081365892
      },
      {
        "date": "2023-05-11",
        "value": 12735.849559704584
      },
      {
        "date": "2023-05-12",
        "value": 12644.981706890396
      },
      {
        "date": "2023-05-15",
        "value": 13054.534816613663
      },
      {
        "date": "2023-05-16",
        "value": 12943.187448680605
      },
      {
        "date": "2023-05-17",
        "value": 13242.67261777287
      },
      {
        "date": "2023-05-18",
        "value": 13311.78772694182
      },
      {
        "date": "2023-05-19",
        "value": 13343.783327534336
      },
      {
        "date": "2023-05-22",
        "value": 13380.899116845358
      },
      {
        "date": "2023-05-23",
        "value": 13016.13836024545
      },
      {
        "date": "2023-05-24",
        "value": 12923.992319884343
      },
      {
        "date": "2023-05-25",
        "value": 12993.102470032742
      },
      {
        "date": "2023-05-26",
        "value": 13149.242191089157
      },
      {
        "date": "2023-05-30",
        "value": 13105.728025512717
      },
      {
        "date": "2023-05-31",
        "value": 12994.379417824523
      },
      {
        "date": "2023-06-01",
        "value": 13396.253484225173
      },
      {
        "date": "2023-06-02",
        "value": 13540.878359563081
      },
      {
        "date": "2023-06-05",
        "value": 13323.305052170606
      },
      {
        "date": "2023-06-06",
        "value": 13497.36543374178
      },
      {
        "date": "2023-06-07",
        "value": 13576.715961327183
      },
      {
        "date": "2023-06-08",
        "value": 13575.437773780264
      },
      {
        "date": "2023-06-09",
        "value": 13604.87451976867
      },
      {
        "date": "2023-06-12",
        "value": 13595.913569633723
      },
      {
        "date": "2023-06-13",
        "value": 13661.186677631089
      },
      {
        "date": "2023-06-14",
        "value": 13400.095485396761
      },
      {
        "date": "2023-06-15",
        "value": 13490.964577966088
      },
      {
        "date": "2023-06-16",
        "value": 13603.592612956341
      },
      {
        "date": "2023-06-20",
        "value": 13313.065914488747
      },
      {
        "date": "2023-06-21",
        "value": 13444.892797540673
      },
      {
        "date": "2023-06-22",
        "value": 13415.454811797132
      },
      {
        "date": "2023-06-23",
        "value": 13282.349741198286
      },
      {
        "date": "2023-06-26",
        "value": 13368.099884804247
      },
      {
        "date": "2023-06-27",
        "value": 13368.099884804247
      },
      {
        "date": "2023-06-28",
        "value": 13368.099884804247
      },
      {
        "date": "2023-06-29",
        "value": 13368.099884804247
      },
      {
        "date": "2023-06-30",
        "value": 13368.099884804247
      },
      {
        "date": "2023-07-03",
        "value": 13368.099884804247
      },
      {
        "date": "2023-07-05",
        "value": 13368.099884804247
      },
      {
        "date": "2023-07-06",
        "value": 13368.099884804247
      },
      {
        "date": "2023-07-07",
        "value": 13368.099884804247
      },
      {
        "date": "2023-07-10",
        "value": 13368.099884804247
      },
      {
        "date": "2023-07-11",
        "value": 13368.099884804247
      },
      {
        "date": "2023-07-12",
        "value": 13368.099884804247
      },
      {
        "date": "2023-07-13",
        "value": 13368.099884804247
      },
      {
        "date": "2023-07-14",
        "value": 13368.099884804247
      },
      {
        "date": "2023-07-17",
        "value": 13368.099884804247
      },
      {
        "date": "2023-07-18",
        "value": 13368.099884804247
      },
      {
        "date": "2023-07-19",
        "value": 13368.099884804247
      },
      {
        "date": "2023-07-20",
        "value": 13368.099884804247
      },
      {
        "date": "2023-07-21",
        "value": 13368.099884804247
      },
      {
        "date": "2023-07-24",
        "value": 13368.099884804247
      },
      {
        "date": "2023-07-25",
        "value": 13368.099884804247
      },
      {
        "date": "2023-07-26",
        "value": 13368.099884804247
      },
      {
        "date": "2023-07-27",
        "value": 13368.099884804247
      },
      {
        "date": "2023-07-28",
        "value": 13368.099884804247
      },
      {
        "date": "2023-07-31",
        "value": 13368.099884804247
      },
      {
        "date": "2023-08-01",
        "value": 13368.099884804247
      },
      {
        "date": "2023-08-02",
        "value": 13368.099884804247
      },
      {
        "date": "2023-08-03",
        "value": 13368.099884804247
      },
      {
        "date": "2023-08-04",
        "value": 13368.099884804247
      },
      {
        "date": "2023-08-07",
        "value": 13368.099884804247
      },
      {
        "date": "2023-08-08",
        "value": 13368.099884804247
      },
      {
        "date": "2023-08-09",
        "value": 13368.099884804247
      },
      {
        "date": "2023-08-10",
        "value": 13368.099884804247
      },
      {
        "date": "2023-08-11",
        "value": 13368.099884804247
      },
      {
        "date": "2023-08-14",
        "value": 13368.099884804247
      },
      {
        "date": "2023-08-15",
        "value": 13368.099884804247
      },
      {
        "date": "2023-08-16",
        "value": 13368.099884804247
      },
      {
        "date": "2023-08-17",
        "value": 13368.099884804247
      },
      {
        "date": "2023-08-18",
        "value": 13368.099884804247
      },
      {
        "date": "2023-08-21",
        "value": 13368.099884804247
      },
      {
        "date": "2023-08-22",
        "value": 13368.099884804247
      },
      {
        "date": "2023-08-23",
        "value": 13368.099884804247
      },
      {
        "date": "2023-08-24",
        "value": 13368.099884804247
      },
      {
        "date": "2023-08-25",
        "value": 13368.099884804247
      },
      {
        "date": "2023-08-28",
        "value": 13368.099884804247
      },
      {
        "date": "2023-08-29",
        "value": 13368.099884804247
      },
      {
        "date": "2023-08-30",
        "value": 13368.099884804247
      },
      {
        "date": "2023-08-31",
        "value": 13368.099884804247
      },
      {
        "date": "2023-09-01",
        "value": 13368.099884804247
      },
      {
        "date": "2023-09-05",
        "value": 13368.099884804247
      },
      {
        "date": "2023-09-06",
        "value": 13368.099884804247
      },
      {
        "date": "2023-09-07",
        "value": 13368.099884804247
      },
      {
        "date": "2023-09-08",
        "value": 13368.099884804247
      },
      {
        "date": "2023-09-11",
        "value": 13368.099884804247
      },
      {
        "date": "2023-09-12",
        "value": 13368.099884804247
      },
      {
        "date": "2023-09-13",
        "value": 13368.099884804247
      },
      {
        "date": "2023-09-14",
        "value": 13368.099884804247
      },
      {
        "date": "2023-09-15",
        "value": 13368.099884804247
      },
      {
        "date": "2023-09-18",
        "value": 13368.099884804247
      },
      {
        "date": "2023-09-19",
        "value": 13368.099884804247
      },
      {
        "date": "2023-09-20",
        "value": 13368.099884804247
      },
      {
        "date": "2023-09-21",
        "value": 13368.099884804247
      },
      {
        "date": "2023-09-22",
        "value": 13368.099884804247
      },
      {
        "date": "2023-09-25",
        "value": 13368.099884804247
      },
      {
        "date": "2023-09-26",
        "value": 13368.099884804247
      },
      {
        "date": "2023-09-27",
        "value": 13368.099884804247
      },
      {
        "date": "2023-09-28",
        "value": 13368.099884804247
      },
      {
        "date": "2023-09-29",
        "value": 13368.099884804247
      },
      {
        "date": "2023-10-02",
        "value": 13368.099884804247
      },
      {
        "date": "2023-10-03",
        "value": 13368.099884804247
      },
      {
        "date": "2023-10-04",
        "value": 13368.099884804247
      },
      {
        "date": "2023-10-05",
        "value": 13368.099884804247
      },
      {
        "date": "2023-10-06",
        "value": 13368.099884804247
      },
      {
        "date": "2023-10-09",
        "value": 13368.099884804247
      },
      {
        "date": "2023-10-10",
        "value": 13368.099884804247
      },
      {
        "date": "2023-10-11",
        "value": 13368.099884804247
      },
      {
        "date": "2023-10-12",
        "value": 13368.099884804247
      },
      {
        "date": "2023-10-13",
        "value": 13368.099884804247
      },
      {
        "date": "2023-10-16",
        "value": 13368.099884804247
      },
      {
        "date": "2023-10-17",
        "value": 13368.099884804247
      },
      {
        "date": "2023-10-18",
        "value": 13368.099884804247
      },
      {
        "date": "2023-10-19",
        "value": 13368.099884804247
      },
      {
        "date": "2023-10-20",
        "value": 13368.099884804247
      },
      {
        "date": "2023-10-23",
        "value": 13368.099884804247
      },
      {
        "date": "2023-10-24",
        "value": 13368.099884804247
      },
      {
        "date": "2023-10-25",
        "value": 13368.099884804247
      },
      {
        "date": "2023-10-26",
        "value": 13368.099884804247
      },
      {
        "date": "2023-10-27",
        "value": 13368.099884804247
      },
      {
        "date": "2023-10-30",
        "value": 13368.099884804247
      },
      {
        "date": "2023-10-31",
        "value": 13368.099884804247
      },
      {
        "date": "2023-11-01",
        "value": 13368.099884804247
      },
      {
        "date": "2023-11-02",
        "value": 13368.099884804247
      },
      {
        "date": "2023-11-03",
        "value": 13368.099884804247
      },
      {
        "date": "2023-11-06",
        "value": 13368.099884804247
      },
      {
        "date": "2023-11-07",
        "value": 13368.099884804247
      },
      {
        "date": "2023-11-08",
        "value": 13368.099884804247
      },
      {
        "date": "2023-11-09",
        "value": 13368.099884804247
      },
      {
        "date": "2023-11-10",
        "value": 13368.099884804247
      },
      {
        "date": "2023-11-13",
        "value": 13368.099884804247
      },
      {
        "date": "2023-11-14",
        "value": 13368.099884804247
      },
      {
        "date": "2023-11-15",
        "value": 13368.099884804247
      },
      {
        "date": "2023-11-16",
        "value": 13368.099884804247
      },
      {
        "date": "2023-11-17",
        "value": 13368.099884804247
      },
      {
        "date": "2023-11-20",
        "value": 13368.099884804247
      },
      {
        "date": "2023-11-21",
        "value": 13368.099884804247
      },
      {
        "date": "2023-11-22",
        "value": 13368.099884804247
      },
      {
        "date": "2023-11-24",
        "value": 13368.099884804247
      },
      {
        "date": "2023-11-27",
        "value": 13368.099884804247
      },
      {
        "date": "2023-11-28",
        "value": 13368.099884804247
      },
      {
        "date": "2023-11-29",
        "value": 13368.099884804247
      },
      {
        "date": "2023-11-30",
        "value": 13368.099884804247
      },
      {
        "date": "2023-12-01",
        "value": 13368.099884804247
      },
      {
        "date": "2023-12-04",
        "value": 13368.099884804247
      },
      {
        "date": "2023-12-05",
        "value": 13368.099884804247
      },
      {
        "date": "2023-12-06",
        "value": 13368.099884804247
      },
      {
        "date": "2023-12-07",
        "value": 13368.099884804247
      },
      {
        "date": "2023-12-08",
        "value": 13368.099884804247
      },
      {
        "date": "2023-12-11",
        "value": 13368.099884804247
      },
      {
        "date": "2023-12-12",
        "value": 13368.099884804247
      },
      {
        "date": "2023-12-13",
        "value": 13368.099884804247
      },
      {
        "date": "2023-12-14",
        "value": 13368.099884804247
      },
      {
        "date": "2023-12-15",
        "value": 13368.099884804247
      },
      {
        "date": "2023-12-18",
        "value": 13368.099884804247
      },
      {
        "date": "2023-12-19",
        "value": 13368.099884804247
      },
      {
        "date": "2023-12-20",
        "value": 13368.099884804247
      },
      {
        "date": "2023-12-21",
        "value": 13368.099884804247
      },
      {
        "date": "2023-12-22",
        "value": 13368.099884804247
      },
      {
        "date": "2023-12-26",
        "value": 13368.099884804247
      },
      {
        "date": "2023-12-27",
        "value": 13368.099884804247
      },
      {
        "date": "2023-12-28",
        "value": 13368.099884804247
      },
      {
        "date": "2023-12-29",
        "value": 13368.099884804247
      }
    ],
    "daily_returns": [
      {
        "date": "2023-01-04",
        "return": 3.5795138018203034,
        "value": 10357.95138018203,
        "active_positions": 10,
        "cash": 0
      },
      {
        "date": "2023-01-05",
        "return": 0.7468875880300624,
        "value": 10435.313633414798,
        "active_positions": 9,
        "cash": 0
      },
      {
        "date": "2023-01-06",
        "return": 3.092448600192541,
        "value": 10758.020343797036,
        "active_positions": 9,
        "cash": 0
      },
      {
        "date": "2023-01-09",
        "return": -0.2858073076689679,
        "value": 10727.27313549395,
        "active_positions": 9,
        "cash": 0
      },
      {
        "date": "2023-01-10",
        "return": 1.5086192566016798,
        "value": 10889.10684372427,
        "active_positions": 9,
        "cash": 0
      },
      {
        "date": "2023-01-11",
        "return": -0.024107785191980726,
        "value": 10886.48172123706,
        "active_positions": 8,
        "cash": 0
      },
      {
        "date": "2023-01-12",
        "return": 1.6140460845451126,
        "value": 11062.194553203406,
        "active_positions": 8,
        "cash": 0
      },
      {
        "date": "2023-01-13",
        "return": 1.0462248073715816,
        "value": 11177.929976858728,
        "active_positions": 8,
        "cash": 0
      },
      {
        "date": "2023-01-17",
        "return": -1.466125270221976,
        "value": 11014.047520780285,
        "active_positions": 8,
        "cash": 0
      },
      {
        "date": "2023-01-18",
        "return": -1.7864674086875285,
        "value": 10817.285151444188,
        "active_positions": 8,
        "cash": 0
      },
      {
        "date": "2023-01-19",
        "return": -1.8209412494339692,
        "value": 10620.308744052645,
        "active_positions": 8,
        "cash": 0
      },
      {
        "date": "2023-01-20",
        "return": 1.225896314116001,
        "value": 10750.502717493726,
        "active_positions": 7,
        "cash": 0
      },
      {
        "date": "2023-01-23",
        "return": 0.15363274371799124,
        "value": 10767.019009782089,
        "active_positions": 7,
        "cash": 0
      },
      {
        "date": "2023-01-24",
        "return": 0.34054446523485343,
        "value": 10803.685497090686,
        "active_positions": 7,
        "cash": 0
      },
      {
        "date": "2023-01-25",
        "return": 0.1627164185372491,
        "value": 10821.26486720158,
        "active_positions": 6,
        "cash": 0
      },
      {
        "date": "2023-01-26",
        "return": 0.592162774303667,
        "value": 10885.34436945395,
        "active_positions": 5,
        "cash": 0
      },
      {
        "date": "2023-01-27",
        "return": 0.686710078437852,
        "value": 10960.095126311657,
        "active_positions": 5,
        "cash": 0
      },
      {
        "date": "2023-01-30",
        "return": -1.4194928404555707,
        "value": 10804.517360686543,
        "active_positions": 4,
        "cash": 0
      },
      {
        "date": "2023-01-31",
        "return": -0.5129617976083513,
        "value": 10749.094314210259,
        "active_positions": 4,
        "cash": 0
      },
      {
        "date": "2023-02-01",
        "return": 0.9795627090524943,
        "value": 10854.388433673144,
        "active_positions": 4,
        "cash": 0
      },
      {
        "date": "2023-02-02",
        "return": -1.8201592562935354,
        "value": 10656.821277883588,
        "active_positions": 4,
        "cash": 0
      },
      {
        "date": "2023-02-03",
        "return": -0.8658573890405313,
        "value": 10564.54840341219,
        "active_positions": 3,
        "cash": 0
      },
      {
        "date": "2023-02-06",
        "return": -0.2369690448435995,
        "value": 10539.513693968584,
        "active_positions": 2,
        "cash": 0
      },
      {
        "date": "2023-02-07",
        "return": -0.5849784176617319,
        "value": 10477.859813532365,
        "active_positions": 2,
        "cash": 0
      },
      {
        "date": "2023-02-08",
        "return": -0.6764377089548693,
        "value": 10406.983618662203,
        "active_positions": 2,
        "cash": 0
      },
      {
        "date": "2023-02-09",
        "return": -0.7360497657087346,
        "value": 10330.383040119694,
        "active_positions": 1,
        "cash": 0
      },
      {
        "date": "2023-02-10",
        "return": 0.6188884993212528,
        "value": 10394.316592690828,
        "active_positions": 1,
        "cash": 0
      },
      {
        "date": "2023-02-13",
        "return": 1.7099369060905225,
        "value": 10572.05284824514,
        "active_positions": 1,
        "cash": 0
      },
      {
        "date": "2023-02-14",
        "return": 1.040160149482845,
        "value": 10682.019128954851,
        "active_positions": 1,
        "cash": 0
      },
      {
        "date": "2023-02-15",
        "return": 1.4723371570847645,
        "value": 10839.294465717356,
        "active_positions": 1,
        "cash": 0
      },
      {
        "date": "2023-02-16",
        "return": -0.8493790469802774,
        "value": 10747.22776968506,
        "active_positions": 1,
        "cash": 0
      },
      {
        "date": "2023-02-17",
        "return": -1.20164991104337,
        "value": 10618.08371675101,
        "active_positions": 1,
        "cash": 0
      },
      {
        "date": "2023-02-21",
        "return": -0.93930151592672,
        "value": 10518.3478954372,
        "active_positions": 1,
        "cash": 0
      },
      {
        "date": "2023-02-22",
        "return": 1.1305584701187432,
        "value": 10637.263968485622,
        "active_positions": 1,
        "cash": 0
      },
      {
        "date": "2023-02-23",
        "return": -0.30050816228605587,
        "value": 10605.29812201641,
        "active_positions": 1,
        "cash": 0
      },
      {
        "date": "2023-02-24",
        "return": 0.7354504708657691,
        "value": 10683.294836991498,
        "active_positions": 1,
        "cash": 0
      },
      {
        "date": "2023-02-27",
        "return": 0.347105611968157,
        "value": 10720.3771529138,
        "active_positions": 1,
        "cash": 0
      },
      {
        "date": "2023-02-28",
        "return": 1.037703304883583,
        "value": 10831.62286092557,
        "active_positions": 1,
        "cash": 0
      },
      {
        "date": "2023-03-01",
        "return": -0.6728813006436429,
        "value": 10758.73889613816,
        "active_positions": 1,
        "cash": 0
      },
      {
        "date": "2023-03-02",
        "return": 1.8778269384737294,
        "value": 10960.769393369894,
        "active_positions": 1,
        "cash": 0
      },
      {
        "date": "2023-03-03",
        "return": 0.7699175982651939,
        "value": 11045.158285834714,
        "active_positions": 1,
        "cash": 0
      },
      {
        "date": "2023-03-06",
        "return": 0.8806681224741595,
        "value": 11142.429473934873,
        "active_positions": 1,
        "cash": 0
      },
      {
        "date": "2023-03-07",
        "return": -0.7695821078029133,
        "value": 11056.679330328912,
        "active_positions": 1,
        "cash": 0
      },
      {
        "date": "2023-03-08",
        "return": 0.6829559167199438,
        "value": 11132.191576008145,
        "active_positions": 1,
        "cash": 0
      },
      {
        "date": "2023-03-09",
        "return": 5.265572206976739,
        "value": 11718.365161661835,
        "active_positions": 1,
        "cash": 0
      },
      {
        "date": "2023-03-10",
        "return": -0.6116484896945819,
        "value": 11646.689958133635,
        "active_positions": 1,
        "cash": 0
      },
      {
        "date": "2023-03-13",
        "return": -2.230756432565239,
        "value": 11386.880672711639,
        "active_positions": 1,
        "cash": 0
      },
      {
        "date": "2023-03-14",
        "return": 2.472753299969456,
        "value": 11668.4501403097,
        "active_positions": 1,
        "cash": 0
      },
      {
        "date": "2023-03-15",
        "return": -1.5465529326228402,
        "value": 11487.991382473107,
        "active_positions": 1,
        "cash": 0
      },
      {
        "date": "2023-03-16",
        "return": 2.462126628434375,
        "value": 11770.840277373223,
        "active_positions": 1,
        "cash": 0
      },
      {
        "date": "2023-03-17",
        "return": -1.8266914445518379,
        "value": 11555.823345074585,
        "active_positions": 1,
        "cash": 0
      },
      {
        "date": "2023-03-20",
        "return": -0.4098249414524364,
        "value": 11508.464698816286,
        "active_positions": 1,
        "cash": 0
      },
      {
        "date": "2023-03-21",
        "return": 2.5133867788275985,
        "value": 11797.716929002376,
        "active_positions": 1,
        "cash": 0
      },
      {
        "date": "2023-03-22",
        "return": -2.809723704932873,
        "value": 11466.233679807317,
        "active_positions": 1,
        "cash": 0
      },
      {
        "date": "2023-03-23",
        "return": 2.232389559325006,
        "value": 11722.204683323143,
        "active_positions": 1,
        "cash": 0
      },
      {
        "date": "2023-03-24",
        "return": -0.24020497378284628,
        "value": 11694.047364636795,
        "active_positions": 1,
        "cash": 0
      },
      {
        "date": "2023-03-27",
        "return": 2.1232549515263397,
        "value": 11942.341804340282,
        "active_positions": 1,
        "cash": 0
      },
      {
        "date": "2023-03-28",
        "return": -0.18221034477640713,
        "value": 11920.581622164216,
        "active_positions": 1,
        "cash": 0
      },
      {
        "date": "2023-03-29",
        "return": 0.987772471519537,
        "value": 12038.329845872971,
        "active_positions": 1,
        "cash": 0
      },
      {
        "date": "2023-03-30",
        "return": -0.010648543682919563,
        "value": 12037.04793906064,
        "active_positions": 1,
        "cash": 0
      },
      {
        "date": "2023-03-31",
        "return": 1.6480839746657083,
        "value": 12235.428597167127,
        "active_positions": 1,
        "cash": 0
      },
      {
        "date": "2023-04-03",
        "return": 1.3807460156466125,
        "value": 12404.368790019798,
        "active_positions": 1,
        "cash": 0
      },
      {
        "date": "2023-04-04",
        "return": -1.9294190124850366,
        "value": 12165.036540206396,
        "active_positions": 1,
        "cash": 0
      },
      {
        "date": "2023-04-05",
        "return": -0.8416857317300259,
        "value": 12062.645163387735,
        "active_positions": 1,
        "cash": 0
      },
      {
        "date": "2023-04-06",
        "return": -0.689639862275522,
        "value": 11979.456353896163,
        "active_positions": 1,
        "cash": 0
      },
      {
        "date": "2023-04-10",
        "return": 0.8119626276550348,
        "value": 12076.725062486046,
        "active_positions": 1,
        "cash": 0
      },
      {
        "date": "2023-04-11",
        "return": -0.4768910828194129,
        "value": 12019.132237566433,
        "active_positions": 1,
        "cash": 0
      },
      {
        "date": "2023-04-12",
        "return": 0.20230510018657255,
        "value": 12043.447555081199,
        "active_positions": 1,
        "cash": 0
      },
      {
        "date": "2023-04-13",
        "return": 0.2125509657027845,
        "value": 12069.046019163432,
        "active_positions": 1,
        "cash": 0
      },
      {
        "date": "2023-04-14",
        "return": 1.2088927567102097,
        "value": 12214.94784229312,
        "active_positions": 1,
        "cash": 0
      },
      {
        "date": "2023-04-17",
        "return": 1.3935455321429289,
        "value": 12385.168702202986,
        "active_positions": 1,
        "cash": 0
      },
      {
        "date": "2023-04-18",
        "return": 1.7567446365429829,
        "value": 12602.744489105737,
        "active_positions": 1,
        "cash": 0
      },
      {
        "date": "2023-04-19",
        "return": 0.5686974319343027,
        "value": 12674.415973368523,
        "active_positions": 1,
        "cash": 0
      },
      {
        "date": "2023-04-20",
        "return": 0.7371576479739139,
        "value": 12767.846400052236,
        "active_positions": 1,
        "cash": 0
      },
      {
        "date": "2023-04-21",
        "return": -0.2506048345594386,
        "value": 12735.849559704582,
        "active_positions": 1,
        "cash": 0
      },
      {
        "date": "2023-04-24",
        "return": 0.6431500431962782,
        "value": 12817.760181649235,
        "active_positions": 1,
        "cash": 0
      },
      {
        "date": "2023-04-25",
        "return": -1.7074372675355116,
        "value": 12598.904967444429,
        "active_positions": 1,
        "cash": 0
      },
      {
        "date": "2023-04-26",
        "return": -2.2653377435715623,
        "value": 12313.497217940198,
        "active_positions": 1,
        "cash": 0
      },
      {
        "date": "2023-04-27",
        "return": 1.9228769131836867,
        "value": 12550.270613149485,
        "active_positions": 1,
        "cash": 0
      },
      {
        "date": "2023-04-28",
        "return": 0.9280083293943451,
        "value": 12666.738169801043,
        "active_positions": 1,
        "cash": 0
      },
      {
        "date": "2023-05-01",
        "return": 2.2329854110680243,
        "value": 12949.584585190885,
        "active_positions": 1,
        "cash": 0
      },
      {
        "date": "2023-05-02",
        "return": 0.32616658477957305,
        "value": 12991.821802975544,
        "active_positions": 1,
        "cash": 0
      },
      {
        "date": "2023-05-03",
        "return": 0.25613242049003365,
        "value": 13025.098070625258,
        "active_positions": 1,
        "cash": 0
      },
      {
        "date": "2023-05-04",
        "return": -2.4073912264641,
        "value": 12711.53300243468,
        "active_positions": 1,
        "cash": 0
      },
      {
        "date": "2023-05-05",
        "return": 0.9263004228605989,
        "value": 12829.279986388297,
        "active_positions": 1,
        "cash": 0
      },
      {
        "date": "2023-05-08",
        "return": 0.6783667594779719,
        "value": 12916.309557296316,
        "active_positions": 1,
        "cash": 0
      },
      {
        "date": "2023-05-09",
        "return": 0.07926333664669247,
        "value": 12926.547455223044,
        "active_positions": 1,
        "cash": 0
      },
      {
        "date": "2023-05-10",
        "return": -1.4455396888026062,
        "value": 12739.689081365892,
        "active_positions": 1,
        "cash": 0
      },
      {
        "date": "2023-05-11",
        "return": -0.03013826818524185,
        "value": 12735.849559704584,
        "active_positions": 1,
        "cash": 0
      },
      {
        "date": "2023-05-12",
        "return": -0.7134808902084416,
        "value": 12644.981706890396,
        "active_positions": 1,
        "cash": 0
      },
      {
        "date": "2023-05-15",
        "return": 3.2388588549724573,
        "value": 13054.534816613663,
        "active_positions": 1,
        "cash": 0
      },
      {
        "date": "2023-05-16",
        "return": -0.8529401430019061,
        "value": 12943.187448680605,
        "active_positions": 1,
        "cash": 0
      },
      {
        "date": "2023-05-17",
        "return": 2.313844022422736,
        "value": 13242.67261777287,
        "active_positions": 1,
        "cash": 0
      },
      {
        "date": "2023-05-18",
        "return": 0.5219120880190838,
        "value": 13311.78772694182,
        "active_positions": 1,
        "cash": 0
      },
      {
        "date": "2023-05-19",
        "return": 0.24035539965650043,
        "value": 13343.783327534336,
        "active_positions": 1,
        "cash": 0
      },
      {
        "date": "2023-05-22",
        "return": 0.2781504195623017,
        "value": 13380.899116845358,
        "active_positions": 1,
        "cash": 0
      },
      {
        "date": "2023-05-23",
        "return": -2.72598091813357,
        "value": 13016.13836024545,
        "active_positions": 1,
        "cash": 0
      },
      {
        "date": "2023-05-24",
        "return": -0.7079368535490091,
        "value": 12923.992319884343,
        "active_positions": 1,
        "cash": 0
      },
      {
        "date": "2023-05-25",
        "return": 0.5347430456304815,
        "value": 12993.102470032742,
        "active_positions": 1,
        "cash": 0
      },
      {
        "date": "2023-05-26",
        "return": 1.2017123809847245,
        "value": 13149.242191089157,
        "active_positions": 1,
        "cash": 0
      },
      {
        "date": "2023-05-30",
        "return": -0.33092527268170857,
        "value": 13105.728025512717,
        "active_positions": 1,
        "cash": 0
      },
      {
        "date": "2023-05-31",
        "return": -0.8496178729745797,
        "value": 12994.379417824523,
        "active_positions": 1,
        "cash": 0
      },
      {
        "date": "2023-06-01",
        "return": 3.0926760984783632,
        "value": 13396.253484225173,
        "active_positions": 1,
        "cash": 0
      },
      {
        "date": "2023-06-02",
        "return": 1.0795919583651614,
        "value": 13540.878359563081,
        "active_positions": 1,
        "cash": 0
      },
      {
        "date": "2023-06-05",
        "return": -1.6067887297637256,
        "value": 13323.305052170606,
        "active_positions": 1,
        "cash": 0
      },
      {
        "date": "2023-06-06",
        "return": 1.3064354594419147,
        "value": 13497.36543374178,
        "active_positions": 1,
        "cash": 0
      },
      {
        "date": "2023-06-07",
        "return": 0.5878964156000203,
        "value": 13576.715961327183,
        "active_positions": 1,
        "cash": 0
      },
      {
        "date": "2023-06-08",
        "return": -0.00941455614568313,
        "value": 13575.437773780264,
        "active_positions": 1,
        "cash": 0
      },
      {
        "date": "2023-06-09",
        "return": 0.2168382816004622,
        "value": 13604.87451976867,
        "active_positions": 1,
        "cash": 0
      },
      {
        "date": "2023-06-12",
        "return": -0.06586573159440157,
        "value": 13595.913569633723,
        "active_positions": 1,
        "cash": 0
      },
      {
        "date": "2023-06-13",
        "return": 0.4800935785819649,
        "value": 13661.186677631089,
        "active_positions": 1,
        "cash": 0
      },
      {
        "date": "2023-06-14",
        "return": -1.9111896967328603,
        "value": 13400.095485396761,
        "active_positions": 1,
        "cash": 0
      },
      {
        "date": "2023-06-15",
        "return": 0.6781227243369585,
        "value": 13490.964577966088,
        "active_positions": 1,
        "cash": 0
      },
      {
        "date": "2023-06-16",
        "return": 0.8348404914960759,
        "value": 13603.592612956341,
        "active_positions": 1,
        "cash": 0
      },
      {
        "date": "2023-06-20",
        "return": -2.1356615618648487,
        "value": 13313.065914488747,
        "active_positions": 1,
        "cash": 0
      },
      {
        "date": "2023-06-21",
        "return": 0.9902067930757997,
        "value": 13444.892797540673,
        "active_positions": 1,
        "cash": 0
      },
      {
        "date": "2023-06-22",
        "return": -0.2189529227702453,
        "value": 13415.454811797132,
        "active_positions": 1,
        "cash": 0
      },
      {
        "date": "2023-06-23",
        "return": -0.9921771007107194,
        "value": 13282.349741198286,
        "active_positions": 1,
        "cash": 0
      },
      {
        "date": "2023-06-26",
        "return": 0.6455946822420066,
        "value": 13368.099884804247,
        "active_positions": 1,
        "cash": 0
      },
      {
        "date": "2023-06-27",
        "return": 0.0,
        "value": 13368.099884804247,
        "active_positions": 0,
        "cash": 13368.099884804247
      },
      {
        "date": "2023-06-28",
        "return": 0.0,
        "value": 13368.099884804247,
        "active_positions": 0,
        "cash": 13368.099884804247
      },
      {
        "date": "2023-06-29",
        "return": 0.0,
        "value": 13368.099884804247,
        "active_positions": 0,
        "cash": 13368.099884804247
      },
      {
        "date": "2023-06-30",
        "return": 0.0,
        "value": 13368.099884804247,
        "active_positions": 0,
        "cash": 13368.099884804247
      },
      {
        "date": "2023-07-03",
        "return": 0.0,
        "value": 13368.099884804247,
        "active_positions": 0,
        "cash": 13368.099884804247
      },
      {
        "date": "2023-07-05",
        "return": 0.0,
        "value": 13368.099884804247,
        "active_positions": 0,
        "cash": 13368.099884804247
      },
      {
        "date": "2023-07-06",
        "return": 0.0,
        "value": 13368.099884804247,
        "active_positions": 0,
        "cash": 13368.099884804247
      },
      {
        "date": "2023-07-07",
        "return": 0.0,
        "value": 13368.099884804247,
        "active_positions": 0,
        "cash": 13368.099884804247
      },
      {
        "date": "2023-07-10",
        "return": 0.0,
        "value": 13368.099884804247,
        "active_positions": 0,
        "cash": 13368.099884804247
      },
      {
        "date": "2023-07-11",
        "return": 0.0,
        "value": 13368.099884804247,
        "active_positions": 0,
        "cash": 13368.099884804247
      },
      {
        "date": "2023-07-12",
        "return": 0.0,
        "value": 13368.099884804247,
        "active_positions": 0,
        "cash": 13368.099884804247
      },
      {
        "date": "2023-07-13",
        "return": 0.0,
        "value": 13368.099884804247,
        "active_positions": 0,
        "cash": 13368.099884804247
      },
      {
        "date": "2023-07-14",
        "return": 0.0,
        "value": 13368.099884804247,
        "active_positions": 0,
        "cash": 13368.099884804247
      },
      {
        "date": "2023-07-17",
        "return": 0.0,
        "value": 13368.099884804247,
        "active_positions": 0,
        "cash": 13368.099884804247
      },
      {
        "date": "2023-07-18",
        "return": 0.0,
        "value": 13368.099884804247,
        "active_positions": 0,
        "cash": 13368.099884804247
      },
      {
        "date": "2023-07-19",
        "return": 0.0,
        "value": 13368.099884804247,
        "active_positions": 0,
        "cash": 13368.099884804247
      },
      {
        "date": "2023-07-20",
        "return": 0.0,
        "value": 13368.099884804247,
        "active_positions": 0,
        "cash": 13368.099884804247
      },
      {
        "date": "2023-07-21",
        "return": 0.0,
        "value": 13368.099884804247,
        "active_positions": 0,
        "cash": 13368.099884804247
      },
      {
        "date": "2023-07-24",
        "return": 0.0,
        "value": 13368.099884804247,
        "active_positions": 0,
        "cash": 13368.099884804247
      },
      {
        "date": "2023-07-25",
        "return": 0.0,
        "value": 13368.099884804247,
        "active_positions": 0,
        "cash": 13368.099884804247
      },
      {
        "date": "2023-07-26",
        "return": 0.0,
        "value": 13368.099884804247,
        "active_positions": 0,
        "cash": 13368.099884804247
      },
      {
        "date": "2023-07-27",
        "return": 0.0,
        "value": 13368.099884804247,
        "active_positions": 0,
        "cash": 13368.099884804247
      },
      {
        "date": "2023-07-28",
        "return": 0.0,
        "value": 13368.099884804247,
        "active_positions": 0,
        "cash": 13368.099884804247
      },
      {
        "date": "2023-07-31",
        "return": 0.0,
        "value": 13368.099884804247,
        "active_positions": 0,
        "cash": 13368.099884804247
      },
      {
        "date": "2023-08-01",
        "return": 0.0,
        "value": 13368.099884804247,
        "active_positions": 0,
        "cash": 13368.099884804247
      },
      {
        "date": "2023-08-02",
        "return": 0.0,
        "value": 13368.099884804247,
        "active_positions": 0,
        "cash": 13368.099884804247
      },
      {
        "date": "2023-08-03",
        "return": 0.0,
        "value": 13368.099884804247,
        "active_positions": 0,
        "cash": 13368.099884804247
      },
      {
        "date": "2023-08-04",
        "return": 0.0,
        "value": 13368.099884804247,
        "active_positions": 0,
        "cash": 13368.099884804247
      },
      {
        "date": "2023-08-07",
        "return": 0.0,
        "value": 13368.099884804247,
        "active_positions": 0,
        "cash": 13368.099884804247
      },
      {
        "date": "2023-08-08",
        "return": 0.0,
        "value": 13368.099884804247,
        "active_positions": 0,
        "cash": 13368.099884804247
      },
      {
        "date": "2023-08-09",
        "return": 0.0,
        "value": 13368.099884804247,
        "active_positions": 0,
        "cash": 13368.099884804247
      },
      {
        "date": "2023-08-10",
        "return": 0.0,
        "value": 13368.099884804247,
        "active_positions": 0,
        "cash": 13368.099884804247
      },
      {
        "date": "2023-08-11",
        "return": 0.0,
        "value": 13368.099884804247,
        "active_positions": 0,
        "cash": 13368.099884804247
      },
      {
        "date": "2023-08-14",
        "return": 0.0,
        "value": 13368.099884804247,
        "active_positions": 0,
        "cash": 13368.099884804247
      },
      {
        "date": "2023-08-15",
        "return": 0.0,
        "value": 13368.099884804247,
        "active_positions": 0,
        "cash": 13368.099884804247
      },
      {
        "date": "2023-08-16",
        "return": 0.0,
        "value": 13368.099884804247,
        "active_positions": 0,
        "cash": 13368.099884804247
      },
      {
        "date": "2023-08-17",
        "return": 0.0,
        "value": 13368.099884804247,
        "active_positions": 0,
        "cash": 13368.099884804247
      },
      {
        "date": "2023-08-18",
        "return": 0.0,
        "value": 13368.099884804247,
        "active_positions": 0,
        "cash": 13368.099884804247
      },
      {
        "date": "2023-08-21",
        "return": 0.0,
        "value": 13368.099884804247,
        "active_positions": 0,
        "cash": 13368.099884804247
      },
      {
        "date": "2023-08-22",
        "return": 0.0,
        "value": 13368.099884804247,
        "active_positions": 0,
        "cash": 13368.099884804247
      },
      {
        "date": "2023-08-23",
        "return": 0.0,
        "value": 13368.099884804247,
        "active_positions": 0,
        "cash": 13368.099884804247
      },
      {
        "date": "2023-08-24",
        "return": 0.0,
        "value": 13368.099884804247,
        "active_positions": 0,
        "cash": 13368.099884804247
      },
      {
        "date": "2023-08-25",
        "return": 0.0,
        "value": 13368.099884804247,
        "active_positions": 0,
        "cash": 13368.099884804247
      },
      {
        "date": "2023-08-28",
        "return": 0.0,
        "value": 13368.099884804247,
        "active_positions": 0,
        "cash": 13368.099884804247
      },
      {
        "date": "2023-08-29",
        "return": 0.0,
        "value": 13368.099884804247,
        "active_positions": 0,
        "cash": 13368.099884804247
      },
      {
        "date": "2023-08-30",
        "return": 0.0,
        "value": 13368.099884804247,
        "active_positions": 0,
        "cash": 13368.099884804247
      },
      {
        "date": "2023-08-31",
        "return": 0.0,
        "value": 13368.099884804247,
        "active_positions": 0,
        "cash": 13368.099884804247
      },
      {
        "date": "2023-09-01",
        "return": 0.0,
        "value": 13368.099884804247,
        "active_positions": 0,
        "cash": 13368.099884804247
      },
      {
        "date": "2023-09-05",
        "return": 0.0,
        "value": 13368.099884804247,
        "active_positions": 0,
        "cash": 13368.099884804247
      },
      {
        "date": "2023-09-06",
        "return": 0.0,
        "value": 13368.099884804247,
        "active_positions": 0,
        "cash": 13368.099884804247
      },
      {
        "date": "2023-09-07",
        "return": 0.0,
        "value": 13368.099884804247,
        "active_positions": 0,
        "cash": 13368.099884804247
      },
      {
        "date": "2023-09-08",
        "return": 0.0,
        "value": 13368.099884804247,
        "active_positions": 0,
        "cash": 13368.099884804247
      },
      {
        "date": "2023-09-11",
        "return": 0.0,
        "value": 13368.099884804247,
        "active_positions": 0,
        "cash": 13368.099884804247
      },
      {
        "date": "2023-09-12",
        "return": 0.0,
        "value": 13368.099884804247,
        "active_positions": 0,
        "cash": 13368.099884804247
      },
      {
        "date": "2023-09-13",
        "return": 0.0,
        "value": 13368.099884804247,
        "active_positions": 0,
        "cash": 13368.099884804247
      },
      {
        "date": "2023-09-14",
        "return": 0.0,
        "value": 13368.099884804247,
        "active_positions": 0,
        "cash": 13368.099884804247
      },
      {
        "date": "2023-09-15",
        "return": 0.0,
        "value": 13368.099884804247,
        "active_positions": 0,
        "cash": 13368.099884804247
      },
      {
        "date": "2023-09-18",
        "return": 0.0,
        "value": 13368.099884804247,
        "active_positions": 0,
        "cash": 13368.099884804247
      },
      {
        "date": "2023-09-19",
        "return": 0.0,
        "value": 13368.099884804247,
        "active_positions": 0,
        "cash": 13368.099884804247
      },
      {
        "date": "2023-09-20",
        "return": 0.0,
        "value": 13368.099884804247,
        "active_positions": 0,
        "cash": 13368.099884804247
      },
      {
        "date": "2023-09-21",
        "return": 0.0,
        "value": 13368.099884804247,
        "active_positions": 0,
        "cash": 13368.099884804247
      },
      {
        "date": "2023-09-22",
        "return": 0.0,
        "value": 13368.099884804247,
        "active_positions": 0,
        "cash": 13368.099884804247
      },
      {
        "date": "2023-09-25",
        "return": 0.0,
        "value": 13368.099884804247,
        "active_positions": 0,
        "cash": 13368.099884804247
      },
      {
        "date": "2023-09-26",
        "return": 0.0,
        "value": 13368.099884804247,
        "active_positions": 0,
        "cash": 13368.099884804247
      },
      {
        "date": "2023-09-27",
        "return": 0.0,
        "value": 13368.099884804247,
        "active_positions": 0,
        "cash": 13368.099884804247
      },
      {
        "date": "2023-09-28",
        "return": 0.0,
        "value": 13368.099884804247,
        "active_positions": 0,
        "cash": 13368.099884804247
      },
      {
        "date": "2023-09-29",
        "return": 0.0,
        "value": 13368.099884804247,
        "active_positions": 0,
        "cash": 13368.099884804247
      },
      {
        "date": "2023-10-02",
        "return": 0.0,
        "value": 13368.099884804247,
        "active_positions": 0,
        "cash": 13368.099884804247
      },
      {
        "date": "2023-10-03",
        "return": 0.0,
        "value": 13368.099884804247,
        "active_positions": 0,
        "cash": 13368.099884804247
      },
      {
        "date": "2023-10-04",
        "return": 0.0,
        "value": 13368.099884804247,
        "active_positions": 0,
        "cash": 13368.099884804247
      },
      {
        "date": "2023-10-05",
        "return": 0.0,
        "value": 13368.099884804247,
        "active_positions": 0,
        "cash": 13368.099884804247
      },
      {
        "date": "2023-10-06",
        "return": 0.0,
        "value": 13368.099884804247,
        "active_positions": 0,
        "cash": 13368.099884804247
      },
      {
        "date": "2023-10-09",
        "return": 0.0,
        "value": 13368.099884804247,
        "active_positions": 0,
        "cash": 13368.099884804247
      },
      {
        "date": "2023-10-10",
        "return": 0.0,
        "value": 13368.099884804247,
        "active_positions": 0,
        "cash": 13368.099884804247
      },
      {
        "date": "2023-10-11",
        "return": 0.0,
        "value": 13368.099884804247,
        "active_positions": 0,
        "cash": 13368.099884804247
      },
      {
        "date": "2023-10-12",
        "return": 0.0,
        "value": 13368.099884804247,
        "active_positions": 0,
        "cash": 13368.099884804247
      },
      {
        "date": "2023-10-13",
        "return": 0.0,
        "value": 13368.099884804247,
        "active_positions": 0,
        "cash": 13368.099884804247
      },
      {
        "date": "2023-10-16",
        "return": 0.0,
        "value": 13368.099884804247,
        "active_positions": 0,
        "cash": 13368.099884804247
      },
      {
        "date": "2023-10-17",
        "return": 0.0,
        "value": 13368.099884804247,
        "active_positions": 0,
        "cash": 13368.099884804247
      },
      {
        "date": "2023-10-18",
        "return": 0.0,
        "value": 13368.099884804247,
        "active_positions": 0,
        "cash": 13368.099884804247
      },
      {
        "date": "2023-10-19",
        "return": 0.0,
        "value": 13368.099884804247,
        "active_positions": 0,
        "cash": 13368.099884804247
      },
      {
        "date": "2023-10-20",
        "return": 0.0,
        "value": 13368.099884804247,
        "active_positions": 0,
        "cash": 13368.099884804247
      },
      {
        "date": "2023-10-23",
        "return": 0.0,
        "value": 13368.099884804247,
        "active_positions": 0,
        "cash": 13368.099884804247
      },
      {
        "date": "2023-10-24",
        "return": 0.0,
        "value": 13368.099884804247,
        "active_positions": 0,
        "cash": 13368.099884804247
      },
      {
        "date": "2023-10-25",
        "return": 0.0,
        "value": 13368.099884804247,
        "active_positions": 0,
        "cash": 13368.099884804247
      },
      {
        "date": "2023-10-26",
        "return": 0.0,
        "value": 13368.099884804247,
        "active_positions": 0,
        "cash": 13368.099884804247
      },
      {
        "date": "2023-10-27",
        "return": 0.0,
        "value": 13368.099884804247,
        "active_positions": 0,
        "cash": 13368.099884804247
      },
      {
        "date": "2023-10-30",
        "return": 0.0,
        "value": 13368.099884804247,
        "active_positions": 0,
        "cash": 13368.099884804247
      },
      {
        "date": "2023-10-31",
        "return": 0.0,
        "value": 13368.099884804247,
        "active_positions": 0,
        "cash": 13368.099884804247
      },
      {
        "date": "2023-11-01",
        "return": 0.0,
        "value": 13368.099884804247,
        "active_positions": 0,
        "cash": 13368.099884804247
      },
      {
        "date": "2023-11-02",
        "return": 0.0,
        "value": 13368.099884804247,
        "active_positions": 0,
        "cash": 13368.099884804247
      },
      {
        "date": "2023-11-03",
        "return": 0.0,
        "value": 13368.099884804247,
        "active_positions": 0,
        "cash": 13368.099884804247
      },
      {
        "date": "2023-11-06",
        "return": 0.0,
        "value": 13368.099884804247,
        "active_positions": 0,
        "cash": 13368.099884804247
      },
      {
        "date": "2023-11-07",
        "return": 0.0,
        "value": 13368.099884804247,
        "active_positions": 0,
        "cash": 13368.099884804247
      },
      {
        "date": "2023-11-08",
        "return": 0.0,
        "value": 13368.099884804247,
        "active_positions": 0,
        "cash": 13368.099884804247
      },
      {
        "date": "2023-11-09",
        "return": 0.0,
        "value": 13368.099884804247,
        "active_positions": 0,
        "cash": 13368.099884804247
      },
      {
        "date": "2023-11-10",
        "return": 0.0,
        "value": 13368.099884804247,
        "active_positions": 0,
        "cash": 13368.099884804247
      },
      {
        "date": "2023-11-13",
        "return": 0.0,
        "value": 13368.099884804247,
        "active_positions": 0,
        "cash": 13368.099884804247
      },
      {
        "date": "2023-11-14",
        "return": 0.0,
        "value": 13368.099884804247,
        "active_positions": 0,
        "cash": 13368.099884804247
      },
      {
        "date": "2023-11-15",
        "return": 0.0,
        "value": 13368.099884804247,
        "active_positions": 0,
        "cash": 13368.099884804247
      },
      {
        "date": "2023-11-16",
        "return": 0.0,
        "value": 13368.099884804247,
        "active_positions": 0,
        "cash": 13368.099884804247
      },
      {
        "date": "2023-11-17",
        "return": 0.0,
        "value": 13368.099884804247,
        "active_positions": 0,
        "cash": 13368.099884804247
      },
      {
        "date": "2023-11-20",
        "return": 0.0,
        "value": 13368.099884804247,
        "active_positions": 0,
        "cash": 13368.099884804247
      },
      {
        "date": "2023-11-21",
        "return": 0.0,
        "value": 13368.099884804247,
        "active_positions": 0,
        "cash": 13368.099884804247
      },
      {
        "date": "2023-11-22",
        "return": 0.0,
        "value": 13368.099884804247,
        "active_positions": 0,
        "cash": 13368.099884804247
      },
      {
        "date": "2023-11-24",
        "return": 0.0,
        "value": 13368.099884804247,
        "active_positions": 0,
        "cash": 13368.099884804247
      },
      {
        "date": "2023-11-27",
        "return": 0.0,
        "value": 13368.099884804247,
        "active_positions": 0,
        "cash": 13368.099884804247
      },
      {
        "date": "2023-11-28",
        "return": 0.0,
        "value": 13368.099884804247,
        "active_positions": 0,
        "cash": 13368.099884804247
      },
      {
        "date": "2023-11-29",
        "return": 0.0,
        "value": 13368.099884804247,
        "active_positions": 0,
        "cash": 13368.099884804247
      },
      {
        "date": "2023-11-30",
        "return": 0.0,
        "value": 13368.099884804247,
        "active_positions": 0,
        "cash": 13368.099884804247
      },
      {
        "date": "2023-12-01",
        "return": 0.0,
        "value": 13368.099884804247,
        "active_positions": 0,
        "cash": 13368.099884804247
      },
      {
        "date": "2023-12-04",
        "return": 0.0,
        "value": 13368.099884804247,
        "active_positions": 0,
        "cash": 13368.099884804247
      },
      {
        "date": "2023-12-05",
        "return": 0.0,
        "value": 13368.099884804247,
        "active_positions": 0,
        "cash": 13368.099884804247
      },
      {
        "date": "2023-12-06",
        "return": 0.0,
        "value": 13368.099884804247,
        "active_positions": 0,
        "cash": 13368.099884804247
      },
      {
        "date": "2023-12-07",
        "return": 0.0,
        "value": 13368.099884804247,
        "active_positions": 0,
        "cash": 13368.099884804247
      },
      {
        "date": "2023-12-08",
        "return": 0.0,
        "value": 13368.099884804247,
        "active_positions": 0,
        "cash": 13368.099884804247
      },
      {
        "date": "2023-12-11",
        "return": 0.0,
        "value": 13368.099884804247,
        "active_positions": 0,
        "cash": 13368.099884804247
      },
      {
        "date": "2023-12-12",
        "return": 0.0,
        "value": 13368.099884804247,
        "active_positions": 0,
        "cash": 13368.099884804247
      },
      {
        "date": "2023-12-13",
        "return": 0.0,
        "value": 13368.099884804247,
        "active_positions": 0,
        "cash": 13368.099884804247
      },
      {
        "date": "2023-12-14",
        "return": 0.0,
        "value": 13368.099884804247,
        "active_positions": 0,
        "cash": 13368.099884804247
      },
      {
        "date": "2023-12-15",
        "return": 0.0,
        "value": 13368.099884804247,
        "active_positions": 0,
        "cash": 13368.099884804247
      },
      {
        "date": "2023-12-18",
        "return": 0.0,
        "value": 13368.099884804247,
        "active_positions": 0,
        "cash": 13368.099884804247
      },
      {
        "date": "2023-12-19",
        "return": 0.0,
        "value": 13368.099884804247,
        "active_positions": 0,
        "cash": 13368.099884804247
      },
      {
        "date": "2023-12-20",
        "return": 0.0,
        "value": 13368.099884804247,
        "active_positions": 0,
        "cash": 13368.099884804247
      },
      {
        "date": "2023-12-21",
        "return": 0.0,
        "value": 13368.099884804247,
        "active_positions": 0,
        "cash": 13368.099884804247
      },
      {
        "date": "2023-12-22",
        "return": 0.0,
        "value": 13368.099884804247,
        "active_positions": 0,
        "cash": 13368.099884804247
      },
      {
        "date": "2023-12-26",
        "return": 0.0,
        "value": 13368.099884804247,
        "active_positions": 0,
        "cash": 13368.099884804247
      },
      {
        "date": "2023-12-27",
        "return": 0.0,
        "value": 13368.099884804247,
        "active_positions": 0,
        "cash": 13368.099884804247
      },
      {
        "date": "2023-12-28",
        "return": 0.0,
        "value": 13368.099884804247,
        "active_positions": 0,
        "cash": 13368.099884804247
      },
      {
        "date": "2023-12-29",
        "return": 0.0,
        "value": 13368.099884804247,
        "active_positions": 0,
        "cash": 13368.099884804247
      }
    ],
    "trade_log": [
      {
        "date": "2023-01-03",
        "ticker": "ROIV",
        "action": "BUY",
        "price": 7.150000095367432,
        "reason": "ì´ˆê¸° ë§¤ìˆ˜",
        "position_value": 1000.0
      },
      {
        "date": "2023-01-03",
        "ticker": "TME",
        "action": "BUY",
        "price": 8.416319847106934,
        "reason": "ì´ˆê¸° ë§¤ìˆ˜",
        "position_value": 1000.0
      },
      {
        "date": "2023-01-03",
        "ticker": "DB",
        "action": "BUY",
        "price": 10.730493545532227,
        "reason": "ì´ˆê¸° ë§¤ìˆ˜",
        "position_value": 1000.0
      },
      {
        "date": "2023-01-03",
        "ticker": "UHS",
        "action": "BUY",
        "price": 140.72950744628906,
        "reason": "ì´ˆê¸° ë§¤ìˆ˜",
        "position_value": 1000.0
      },
      {
        "date": "2023-01-03",
        "ticker": "HAL",
        "action": "BUY",
        "price": 35.4029541015625,
        "reason": "ì´ˆê¸° ë§¤ìˆ˜",
        "position_value": 1000.0
      },
      {
        "date": "2023-01-03",
        "ticker": "CAT",
        "action": "BUY",
        "price": 226.9651641845703,
        "reason": "ì´ˆê¸° ë§¤ìˆ˜",
        "position_value": 1000.0
      },
      {
        "date": "2023-01-03",
        "ticker": "GE",
        "action": "BUY",
        "price": 52.20120620727539,
        "reason": "ì´ˆê¸° ë§¤ìˆ˜",
        "position_value": 1000.0
      },
      {
        "date": "2023-01-03",
        "ticker": "ORCL",
        "action": "BUY",
        "price": 80.66852569580078,
        "reason": "ì´ˆê¸° ë§¤ìˆ˜",
        "position_value": 1000.0
      },
      {
        "date": "2023-01-03",
        "ticker": "MRK",
        "action": "BUY",
        "price": 102.29607391357422,
        "reason": "ì´ˆê¸° ë§¤ìˆ˜",
        "position_value": 1000.0
      },
      {
        "date": "2023-01-03",
        "ticker": "ASML",
        "action": "BUY",
        "price": 534.7266845703125,
        "reason": "ì´ˆê¸° ë§¤ìˆ˜",
        "position_value": 1000.0
      },
      {
        "date": "2023-01-04",
        "ticker": "ASML",
        "action": "SELL",
        "price": 555.4125366210938,
        "reason": "íŠ¸ë ˆì¼ë§ ìŠ¤íƒ‘ (MA20 2ì¼ ì´íƒˆ)",
        "position_value": 1038.6849069771104
      },
      {
        "date": "2023-01-10",
        "ticker": "MRK",
        "action": "SELL",
        "price": 101.99234771728516,
        "reason": "íŠ¸ë ˆì¼ë§ ìŠ¤íƒ‘ (MA20 2ì¼ ì´íƒˆ)",
        "position_value": 1109.5662873222677
      },
      {
        "date": "2023-01-19",
        "ticker": "TME",
        "action": "SELL",
        "price": 8.054221153259277,
        "reason": "íŠ¸ë ˆì¼ë§ ìŠ¤íƒ‘ (MA20 2ì¼ ì´íƒˆ)",
        "position_value": 1198.386588663428
      },
      {
        "date": "2023-01-24",
        "ticker": "ROIV",
        "action": "SELL",
        "price": 8.609999656677246,
        "reason": "íŠ¸ë ˆì¼ë§ ìŠ¤íƒ‘ (MA20 2ì¼ ì´íƒˆ)",
        "position_value": 1617.6444793920707
      },
      {
        "date": "2023-01-25",
        "ticker": "HAL",
        "action": "SELL",
        "price": 37.63091278076172,
        "reason": "íŠ¸ë ˆì¼ë§ ìŠ¤íƒ‘ (MA20 2ì¼ ì´íƒˆ)",
        "position_value": 1755.0170606003649
      },
      {
        "date": "2023-01-27",
        "ticker": "UHS",
        "action": "SELL",
        "price": 143.2952117919922,
        "reason": "íŠ¸ë ˆì¼ë§ ìŠ¤íƒ‘ (MA20 2ì¼ ì´íƒˆ)",
        "position_value": 2054.355582768084
      },
      {
        "date": "2023-02-02",
        "ticker": "CAT",
        "action": "SELL",
        "price": 233.79457092285156,
        "reason": "íŠ¸ë ˆì¼ë§ ìŠ¤íƒ‘ (MA20 2ì¼ ì´íƒˆ)",
        "position_value": 2516.7095939469323
      },
      {
        "date": "2023-02-03",
        "ticker": "DB",
        "action": "SELL",
        "price": 11.39026927947998,
        "reason": "íŠ¸ë ˆì¼ë§ ìŠ¤íƒ‘ (MA20 2ì¼ ì´íƒˆ)",
        "position_value": 3382.370304988502
      },
      {
        "date": "2023-02-08",
        "ticker": "ORCL",
        "action": "SELL",
        "price": 83.843505859375,
        "reason": "íŠ¸ë ˆì¼ë§ ìŠ¤íƒ‘ (MA20 2ì¼ ì´íƒˆ)",
        "position_value": 5040.965551623882
      },
      {
        "date": "2023-06-26",
        "ticker": "GE",
        "action": "SELL",
        "price": 82.26665496826172,
        "reason": "íŠ¸ë ˆì¼ë§ ìŠ¤íƒ‘ (MA20 2ì¼ ì´íƒˆ)",
        "position_value": 13368.099884804247
      }
    ],
    "final_sales": [],
    "total_trades": 20
  },
  "run_date": "2025-11-03 18:29:49"
}